pubsubx/__init__.py
pubsubx/__main__.py
pubsubx/client.py
pubsubx/server.py
pubsubx-0.1.2.dist-info/METADATA
pubsubx-0.1.2.dist-info/WHEEL
pubsubx-0.1.2.dist-info/entry_points.txt
pubsubx-0.1.2.dist-info/top_level.txt
pubsubx-0.1.2.dist-info/RECORD
