Metadata-Version: 2.1
Name: pubsubx
Version: 0.1.2
Summary: A publish-subscribe messaging system
Home-page: https://github.com/yourusername/simplepubsub
Author: xxparthparekhxx
Author-email: xx.parthparekh.xx@gmail.com
Classifier: Development Status :: 3 - Alpha
Classifier: Intended Audience :: Developers
Classifier: License :: OSI Approved :: MIT License
Classifier: Operating System :: OS Independent
Classifier: Programming Language :: Python :: 3
Classifier: Programming Language :: Python :: 3.6
Classifier: Programming Language :: Python :: 3.7
Classifier: Programming Language :: Python :: 3.8
Classifier: Programming Language :: Python :: 3.9
Requires-Python: >=3.6
